{
  "_id": "",
  "name": "@migrationsverket/link-button",
  "dist-tags": {
    "latest": "0.2.8"
  },
  "versions": [
    "0.2.6",
    "0.2.7",
    "0.2.8"
  ],
  "time": {
    "0.2.6": "2024-08-12T13:40:20Z",
    "0.2.7": "2024-08-13T08:34:36Z",
    "0.2.8": "2024-08-13T08:44:23Z"
  },
  "description": "```bash npm install @migrationsverket/link-button ```",
  "author": {},
  "homepage": "https://github.com/migrationsverket/midas#readme",
  "repository": {
    "type": "git",
    "url": "git+https://github.com/migrationsverket/midas.git"
  },
  "bugs": {
    "url": "https://github.com/migrationsverket/midas/issues"
  },
  "_contentLength": 0,
  "version": "0.2.8",
  "_nodeVersion": "20.11.1",
  "_npmVersion": "10.2.4",
  "dist": {
    "integrity": "sha512-DSkpAco7JXIj9VuVPOnGYqL5OCRe7oBYUN6zzxavfpHRLjpv9q0mh+PFL7+2IyoFhoXIBBx6vHaV4pyuBj+yjQ==",
    "shasum": "30460e9b42da9dbc6dfc7ddc0c219fb1c12e690f",
    "tarball": "https://npm.pkg.github.com/download/@migrationsverket/link-button/0.2.8/30460e9b42da9dbc6dfc7ddc0c219fb1c12e690f"
  },
  "_npmUser": "wilhjelmig",
  "main": "./index.js",
  "dependencies": {
    "@migrationsverket/theme": "^0.5.23"
  },
  "gitHead": "660173f9a53a45cd053cc3ee2523dc3bcc65d9fa",
  "directories": {},
  "_hasShrinkwrap": false,
  "readme": "# LinkButton\n\n```bash\nnpm install @migrationsverket/link-button\n```\n\n```tsx\nimport { LinkButton } from '@migrationsverket/link-button\n;<LinkButton href=\"#\">Hej</LinkButton>\n```\n"
}
