{
  "_id": "@midas-ds/tag@0.1.2",
  "_rev": "1-6cc5fe16b38103c4515c9d985b867973",
  "name": "@midas-ds/tag",
  "dist-tags": {
    "latest": "0.1.2"
  },
  "versions": [
    "0.1.1",
    "0.1.2"
  ],
  "time": {
    "created": "2024-11-15T14:18:02.271Z",
    "modified": "2024-11-15T14:24:05.630Z",
    "0.1.1": "2024-11-15T14:18:02.781Z",
    "0.1.2": "2024-11-15T14:24:05.461Z"
  },
  "bugs": {
    "url": "https://github.com/migrationsverket/midas/issues"
  },
  "homepage": "https://github.com/migrationsverket/midas#readme",
  "repository": {
    "type": "git",
    "url": "git+https://github.com/migrationsverket/midas.git"
  },
  "maintainers": [
    "wilhelmconsid <wilhelm.hjelm@consid.se>"
  ],
  "readmeFilename": "README.md",
  "_contentLength": 0,
  "version": "0.1.2",
  "main": "./index.js",
  "types": "./index.d.ts",
  "exports": {
    ".": {
      "import": "./index.mjs",
      "require": "./index.js",
      "types": "./index.d.ts"
    }
  },
  "dependencies": {
    "lucide-react": "^0.453.0",
    "@midas-ds/button": "1.1.1",
    "react-aria-components": "^1.1.1"
  },
  "peerDependencies": {
    "react": "^18.2.0"
  },
  "publishConfig": {
    "access": "public"
  },
  "gitHead": "1b851fa63eb50dca8a28fc98a02e53cdb2f5bf92",
  "_nodeVersion": "20.11.1",
  "_npmVersion": "10.2.4",
  "dist": {
    "integrity": "sha512-TqvD4uIKO8l28uYoHiB2SzDgsUGAI3KQ/dP85oHZK353u6IsQUFbop4/o5ZBHGzQJKQ4IdCGw4BbhrpGw5e9ew==",
    "shasum": "62b7cc957dab192602c4a675e762765455aab28d",
    "tarball": "https://registry.npmjs.org/@midas-ds/tag/-/tag-0.1.2.tgz",
    "fileCount": 9,
    "unpackedSize": 296292,
    "signatures": [
      {
        "keyid": "SHA256:jl3bwswu80PjjokCgh0o2w5c2U4LhQAE57gj9cz1kzA",
        "sig": "MEUCIQCALrzfn4Kv/+ANRIn2ddX3k/wb9dVg61l6D7gzoLkJvwIgJFFPgpPaLhIuN70/iW0qUgqHx926bCiLcYSyphLa9Pg="
      }
    ]
  },
  "_npmUser": "wilhelmconsid <wilhelm.hjelm@consid.se>",
  "directories": {},
  "_npmOperationalInternal": {
    "host": "s3://npm-registry-packages",
    "tmp": "tmp/tag_0.1.2_1731680645300_0.8977617958276505"
  },
  "_hasShrinkwrap": false
}
